[
    {
        "handle": "comments",
        "versions": [
            "0.3.6",
            "1.5.5",
            "1.5.6"
        ]
    },
    {
        "handle": "retour",
        "versions": [
            "3.1.31"
        ]
    },
    {
        "handle": "seomatic",
        "versions": [
            "3.1.4",
            "3.1.7",
            "3.2.36",
            "3.2.37",
            "3.2.44",
            "3.2.46",
            "3.2.49",
            "3.3.0",
            "3.3.15",
            "3.3.16"
        ]
    },
    {
        "handle": "sprig",
        "versions": [
            "1.1.0",
            "1.999.0"
        ]
    },
    {
        "handle": "transcoder",
        "versions": [
            "1.2.13"
        ]
    }
]
